physkit-0.1.23.dist-info/METADATA
physkit-0.1.23.dist-info/WHEEL
physkit-0.1.23.dist-info/entry_points.txt
physkit-0.1.23.dist-info/licenses/LICENSE
physkit/__init__.py
physkit/cli.py
physkit/config.py
physkit/constants.py
physkit/conversions.py
physkit/custom_units.py
physkit/equations.py
physkit/plot_styler.py
physkit-0.1.23.dist-info/RECORD
