Metadata-Version: 2.1
Name: physkit
Version: 0.1.23
Summary: A Python toolkit providing physical constants, unit conversions, and plotting styles
Keywords: physics,units,pint,plotting
Author: sapphimars
License: GPL-3.0-or-later
Classifier: Programming Language :: Python :: 3
Classifier: License :: OSI Approved :: GNU General Public License v3 (GPLv3)
Classifier: Operating System :: OS Independent
Project-URL: Homepage, https://github.com/sapphimars/physkit
Project-URL: Repository, https://github.com/sapphimars/physkit
Project-URL: Bug Tracker, https://github.com/sapphimars/physkit/issues
Requires-Python: >=3.12
Requires-Dist: pint>=0.24.4
Requires-Dist: matplotlib>=3.10.0
Requires-Dist: pdm-backend>=2.4.3
